dynamic_versioning/__init__.py
dynamic_versioning/commands.py
dynamic_versioning/configuration.py
dynamic_versioning/utils.py
dynamic_versioning-1.1.0.dist-info/LICENSE
dynamic_versioning-1.1.0.dist-info/METADATA
dynamic_versioning-1.1.0.dist-info/WHEEL
dynamic_versioning-1.1.0.dist-info/top_level.txt
dynamic_versioning-1.1.0.dist-info/RECORD
