Metadata-Version: 2.1
Name: dynamic-versioning
Version: 1.1.0
Summary: Provides dynamic versioning of python packages by providing additional options to the standard setuptools commands.
Home-page: https://github.com/timepieces141/dynamic-versioning
Author: Edward Petersen
Author-email: edward.petersen@gmail.com
License: MIT
Classifier: Development Status :: 4 - Beta
Classifier: License :: OSI Approved :: MIT License
Classifier: Programming Language :: Python :: 3
Classifier: Programming Language :: Python :: 3.10
Classifier: Programming Language :: Python :: 3.11
Classifier: Framework :: Setuptools Plugin
Classifier: Intended Audience :: Developers
Classifier: Topic :: Software Development :: Build Tools
Classifier: Topic :: System :: Installation/Setup
Classifier: Topic :: System :: Software Distribution
License-File: LICENSE
Requires-Dist: setuptools >=68.0.0
Requires-Dist: toml ==0.10.2
Requires-Dist: deprecated ==1.2.14
Provides-Extra: dev
Requires-Dist: coverage ; extra == 'dev'
Requires-Dist: isort ; extra == 'dev'
Requires-Dist: mypy ; extra == 'dev'
Requires-Dist: pyfakefs ; extra == 'dev'
Requires-Dist: pylint ; extra == 'dev'
Requires-Dist: pytest ; extra == 'dev'
Requires-Dist: types-setuptools ; extra == 'dev'
Requires-Dist: types-toml ; extra == 'dev'
Requires-Dist: types-Deprecated ; extra == 'dev'
Provides-Extra: dist
Requires-Dist: pip ; extra == 'dist'
Requires-Dist: setuptools ; extra == 'dist'
Requires-Dist: twine ; extra == 'dist'
Provides-Extra: docs
Requires-Dist: sphinx ; extra == 'docs'
Requires-Dist: sphinx-rtd-theme ; extra == 'docs'
